{"chunk_definitions":[{"row":50,"row_count":1,"visible":true,"expansion_state":0,"options":{"engine":"r","label":"Loadout","include":false,"dev":"png"},"document_id":"F658D65D","chunk_id":"ct3hu2kkavpza","chunk_label":"Loadout"},{"row":66,"row_count":1,"visible":true,"expansion_state":0,"options":{"engine":"r","label":"Estimates and Goals","include":false},"document_id":"F658D65D","chunk_id":"c3hatk8ra3e1z","chunk_label":"Estimates and Goals"},{"row":108,"row_count":1,"visible":true,"expansion_state":0,"options":{"engine":"r","label":"Get Data","include":false},"document_id":"F658D65D","chunk_id":"c6txlwohrfswh","chunk_label":"Get Data"},{"row":126,"row_count":1,"visible":true,"expansion_state":0,"options":{"engine":"r","label":"Data Processing: Dispositions","include":false},"document_id":"F658D65D","chunk_id":"cyn15qnj1gsyd","chunk_label":"Data Processing: Dispositions"},{"row":203,"row_count":1,"visible":true,"expansion_state":0,"options":{"engine":"r","label":"Plot Prep: Catch + Flow","include":false},"document_id":"F658D65D","chunk_id":"cfuytwinx2gwa","chunk_label":"Plot Prep: Catch + Flow"}],"doc_write_time":1747160347}